ctox/__init__.py
ctox/__main__.py
ctox/config.py
ctox/main.py
ctox/pkg.py
ctox/shell.py
ctox/subst.py
ctox-0.1.3.dist-info/DESCRIPTION.rst
ctox-0.1.3.dist-info/METADATA
ctox-0.1.3.dist-info/RECORD
ctox-0.1.3.dist-info/WHEEL
ctox-0.1.3.dist-info/entry_points.txt
ctox-0.1.3.dist-info/metadata.json
ctox-0.1.3.dist-info/top_level.txt
